[
  {
    "url": "https://api.github.com/repos/calypsonet/keyple-demo-ticketing/issues/2",
    "repository_url": "https://api.github.com/repos/calypsonet/keyple-demo-ticketing",
    "labels_url": "https://api.github.com/repos/calypsonet/keyple-demo-ticketing/issues/2/labels{/name}",
    "comments_url": "https://api.github.com/repos/calypsonet/keyple-demo-ticketing/issues/2/comments",
    "events_url": "https://api.github.com/repos/calypsonet/keyple-demo-ticketing/issues/2/events",
    "html_url": "https://github.com/calypsonet/keyple-demo-ticketing/pull/2",
    "id": 3376642547,
    "node_id": "PR_kwDOPR5Tt86mfRRo",
    "number": 2,
    "title": "fix: Fix ios compilation",
    "user": {
      "login": "tdassonville",
      "id": 1982823,
      "node_id": "MDQ6VXNlcjE5ODI4MjM=",
      "avatar_url": "https://avatars.githubusercontent.com/u/1982823?v=4",
      "gravatar_id": "",
      "url": "https://api.github.com/users/tdassonville",
      "html_url": "https://github.com/tdassonville",
      "followers_url": "https://api.github.com/users/tdassonville/followers",
      "following_url": "https://api.github.com/users/tdassonville/following{/other_user}",
      "gists_url": "https://api.github.com/users/tdassonville/gists{/gist_id}",
      "starred_url": "https://api.github.com/users/tdassonville/starred{/owner}{/repo}",
      "subscriptions_url": "https://api.github.com/users/tdassonville/subscriptions",
      "organizations_url": "https://api.github.com/users/tdassonville/orgs",
      "repos_url": "https://api.github.com/users/tdassonville/repos",
      "events_url": "https://api.github.com/users/tdassonville/events{/privacy}",
      "received_events_url": "https://api.github.com/users/tdassonville/received_events",
      "type": "User",
      "user_view_type": "public",
      "site_admin": false
    },
    "labels": [

    ],
    "state": "open",
    "locked": false,
    "assignee": null,
    "assignees": [

    ],
    "milestone": null,
    "comments": 0,
    "created_at": "2025-09-02T16:02:31Z",
    "updated_at": "2025-09-03T18:11:33Z",
    "closed_at": null,
    "author_association": "FIRST_TIME_CONTRIBUTOR",
    "type": null,
    "active_lock_reason": null,
    "draft": false,
    "pull_request": {
      "url": "https://api.github.com/repos/calypsonet/keyple-demo-ticketing/pulls/2",
      "html_url": "https://github.com/calypsonet/keyple-demo-ticketing/pull/2",
      "diff_url": "https://github.com/calypsonet/keyple-demo-ticketing/pull/2.diff",
      "patch_url": "https://github.com/calypsonet/keyple-demo-ticketing/pull/2.patch",
      "merged_at": null
    },
    "body": "Fix a few issues with ios build config:\r\n- corrupted PNG file (icon)\r\n- missing materialExtendedIcons dependency\r\n- update all dependencies\r\n- erroneous package folder (folder named \"keyple.demo\" instead of \"keyple\"/\"demo\") ",
    "closed_by": null,
    "reactions": {
      "url": "https://api.github.com/repos/calypsonet/keyple-demo-ticketing/issues/2/reactions",
      "total_count": 0,
      "+1": 0,
      "-1": 0,
      "laugh": 0,
      "hooray": 0,
      "confused": 0,
      "heart": 0,
      "rocket": 0,
      "eyes": 0
    },
    "timeline_url": "https://api.github.com/repos/calypsonet/keyple-demo-ticketing/issues/2/timeline",
    "performed_via_github_app": null,
    "state_reason": null
  }
]
